{
  "date-last-modified": "2017-07-03T16:29:56.553411+00:00",
  "version": "",
  "name": "OrganisationRole",
  "xml:lang": "en",
  "OrganisationRole": [
    {
      "code": "1",
      "name": "Funding",
      "language": "en",
      "description": "The government or organisation which provides funds to the activity. "
    },
    {
      "code": "2",
      "name": "Accountable",
      "language": "en",
      "description": "An organisation responsible for oversight of the activity and its outcomes"
    },
    {
      "code": "3",
      "name": "Extending",
      "language": "en",
      "description": "An organisation that manages the budget and direction of an activity on behalf of the funding organisation"
    },
    {
      "code": "4",
      "name": "Implementing",
      "language": "en",
      "description": "The organisation that physically carries out the activity or intervention. "
    }
  ]
}
